[
    {
        "id":0,
        "name": "Municipalidad",
        "description": "Municipalidad de la ciudad de Tandil ",
        "category": "Turistico",
        "lat": -37.329809,
        "long": -59.136778,
        "imgsrc": "img/municipalidad.jpg"
    },
    {
        "id":1,
        "name": "Iglesia",
        "description": "Iglesia del Santisimo Sacramento",
        "category": "Turistico",
        "lat": -37.32937,
        "long": -59.136301,
        "imgsrc": "img/iglesia.jpg"
    },
    {
        "id":2,
        "name": "Bodegón del Fuerte",
        "description": "Pub con cerveza artesana y comida gourmet",
        "category": "Bar",
        "lat": -37.329148,
        "long": -59.135472,
        "imgsrc": "img/bodegon.jpg"
    }, 
    {
        "id":3,
        "name": "Iglu Helados",
        "description": "Heladería y Cafetería Iglu",
        "category": "Cafeteria",
        "lat":  -37.327858,
        "long": -59.135716,
        "imgsrc": "img/iglu.png"
    },
    {
        "id":4,
        "name": "Cheverry",
        "description": "Cervecería artesanal marplatense",
        "category": "Bar",
        "lat": -37.327572,
        "long": -59.135875,
        "imgsrc": "img/cheverry.jpg"
    },
    {
        "id":5,
        "name": "Rana Baris",
        "description": "Restaurant, Pizzería y Cafetería",
        "category": "Restaurant",
        "lat": -37.328005,
        "long": -59.137328,
        "imgsrc": "img/rana.jpg"
    }, 
    {
        "id":6,
        "name": "Piaf",
        "description": "Cervecería artesanal de época",
        "category": "Bar",
        "lat": -37.328027,
        "long": -59.137409,
        "imgsrc": "img/piaf.jpg"
    }, 
    {
        "id":7,
        "name": "Rectorado",
        "description": "",
        "category": "Turistico",
        "lat": -37.328602,
        "long": -59.138586,
        "imgsrc": "img/rectorado.jpg"
    },
    {
        "id":8,
        "name": "Hotel Plaza",
        "description": "Hotel tradicional de la ciudad de 3 estrellas",
        "category": "Turistico",
        "lat": -37.328203,
        "long":-59.138197,
        "imgsrc": "img/hotel.jpg"
    },
    {
        "id":9,
        "name": "Nice",
        "description": "Nucleo de Inteligencia Comportamental Empresarial",
        "category": "Turistico",
        "lat": -37.321487,
        "long": -59.082222,
        "imgsrc": "img/nice.jpg"
    },
    {
        "id":10,
        "name": "Comedor",
        "description": "Comedor Autogestionado de la UNCPBA",
        "category": "Restautant",
        "lat": -37.321758,
        "long":-59.081157,
        "imgsrc": "img/comedor.jpg"
    },
    {
        "id":11,
        "name": "Biblioteca",
        "description": "Biblioteca Central da la UNCPBA",
        "category": "Turistico",
        "lat": -37.322743,
        "long":-59.079779,
        "imgsrc": "img/hotel.jpg"
    },
    {
        "id":12,
        "name": "Gimnasio",
        "description": "Gimnasio de la UNCPBA donde podés enconrar la Secretaría de Bienestar Estudiantil y la Secretaría de Deportes",
        "category": "Turistico",
        "lat": -37.323072,
        "long": -59.083534,
        "imgsrc": "img/gimnasio.jpg"
    }
]